filonov/__init__.py
filonov/creative_map.py
filonov/exceptions.py
filonov/filonov_service.py
filonov/previews.py
filonov/telemetry.py
filonov/website_previews.py
filonov/entrypoints/__init__.py
filonov/entrypoints/cli.py
filonov/entrypoints/server.py
filonov/entrypoints/streamlit_app.py
filonov/entrypoints/streamlit_cli.py
filonov/entrypoints/tracer.py
filonov/entrypoints/utils.py
filonov-0.11.1.dist-info/METADATA
filonov-0.11.1.dist-info/WHEEL
filonov-0.11.1.dist-info/entry_points.txt
filonov-0.11.1.dist-info/top_level.txt
filonov-0.11.1.dist-info/RECORD
