Metadata-Version: 2.4
Name: filonov
Version: 0.11.1
Summary: AI Creative Concept Analysis library
Author-email: Andrei Markin <amarkin@google.com>, Sergei Dorogin <segy@google.com>, "Google Inc. (gTech gPS CSE team)" <no-reply@google.com>
Classifier: Development Status :: 4 - Beta
Classifier: Programming Language :: Python
Requires-Python: >=3.10
Requires-Dist: media-fetching>=0.6.0
Requires-Dist: media-similarity>=0.9.0
Requires-Dist: typer
Requires-Dist: opentelemetry-api
Requires-Dist: opentelemetry-sdk
Requires-Dist: opentelemetry-exporter-otlp
Provides-Extra: server
Requires-Dist: media-tagging[server]; extra == "server"
Requires-Dist: media-similarity[server]; extra == "server"
Provides-Extra: ui
Requires-Dist: streamlit; extra == "ui"
Provides-Extra: playwright
Requires-Dist: playwright; extra == "playwright"
Provides-Extra: all
Requires-Dist: filonov[playwright,server,ui]; extra == "all"
